zelf/modules/__init__.py
zelf/modules/fnd.py
zelf/modules/irc.py
zelf/modules/log.py
zelf/modules/mod.py
zelf/modules/req.py
zelf/modules/rss.py
zelf/modules/shp.py
zelf/modules/sts.py
zelf/modules/tdo.py
zelf/modules/thr.py
zelf/modules/udp.py
zelf-110.data/data/share/zelf/README.rst
zelf-110.data/scripts/zelf
zelf-110.dist-info/METADATA
zelf-110.dist-info/WHEEL
zelf-110.dist-info/top_level.txt
zelf-110.dist-info/zip-safe
zelf-110.dist-info/RECORD
