Metadata-Version: 2.1
Name: zelf
Version: 110
Summary: the self
Author-email: Zelf <tehzelf@gmail.com>
License: Public Domain
Project-URL: home, https://pypi.org/project/zelf
Project-URL: bugs, https://github.com/tehzelf/zelf/issues
Project-URL: source, https://github.com/tehzelf/zelf
Classifier: Development Status :: 3 - Alpha
Classifier: License :: Public Domain
Classifier: Operating System :: Unix
Classifier: Programming Language :: Python
Classifier: Topic :: Utilities
Requires-Dist: opv
Requires-Dist: opr
